{"stat.chestOpened":1,"stat.pickup.tconstruct.book":2,"stat.walkOneCm":44787,"stat.playerKills":2,"stat.drop.gravestone.death_info":6,"stat.pickup.minecraft.stick":4,"stat.pickup.minecraft.wooden_axe":2,"stat.leaveGame":2,"stat.pickup.minecraft.arrow":2,"stat.craftItem.minecraft.crafting_table":1,"stat.mineBlock.minecraft.yellow_flower":1,"stat.useItem.minecraft.apple":2,"stat.useItem.minecraft.porkchop":3,"stat.talkedToVillager":1,"stat.pickup.gravestone.death_info":2,"stat.pickup.minecraft.log":8,"stat.jump":528,"stat.fallOneCm":13911,"stat.climbOneCm":1216,"stat.pickup.minecraft.porkchop":18,"stat.crouchOneCm":6989,"stat.mineBlock.gravestone.gravestone":5,"stat.pickup.minecraft.dirt":20,"stat.useItem.minecraft.dirt":12,"stat.sprintOneCm":74049,"stat.useItem.minecraft.stone_slab2":4,"stat.pickup.minecraft.apple":2,"stat.craftItem.minecraft.stick":4,"stat.craftItem.minecraft.wooden_axe":1,"stat.craftingTableInteraction":1,"stat.killEntity.Skeleton":1,"stat.craftItem.minecraft.planks":32,"stat.damageTaken":1648,"stat.mobKills":4,"stat.pickup.dynamictrees.oakseed":6,"stat.pickup.minecraft.planks":46,"stat.flyOneCm":121583,"stat.pickup.minecraft.bed":3,"stat.deaths":6,"stat.drop":8,"stat.pickup.minecraft.wheat_seeds":4,"stat.pickup.conarm.book":2,"stat.playOneMinute":20898,"stat.drop.minecraft.wheat_seeds":1,"stat.sneakTime":2271,"stat.damageDealt":811,"stat.timeSinceDeath":544,"stat.drop.minecraft.yellow_flower":1,"stat.useItem.minecraft.wooden_axe":7,"stat.pickup.minecraft.yellow_flower":7,"stat.mineBlock.minecraft.dirt":18,"stat.killEntity.Pig":3,"stat.mineBlock.minecraft.tallgrass":21}